cosmos/__init__.py
cosmos/embeddings.py
cosmos/extraction.py
cosmos/retrieval.py
cosmos_api-0.0.1.dist-info/LICENSE
cosmos_api-0.0.1.dist-info/METADATA
cosmos_api-0.0.1.dist-info/WHEEL
cosmos_api-0.0.1.dist-info/top_level.txt
cosmos_api-0.0.1.dist-info/RECORD
