Metadata-Version: 2.1
Name: cosmos-api
Version: 0.0.1
Summary: The COSMOS api package
Home-page: https://github.com/UW-COSMOS/Cosmos
Author: Ankur Goswami
Author-email: ankur.goswami12@gmail.com
License: UNKNOWN
Platform: UNKNOWN
Classifier: Programming Language :: Python :: 3
Classifier: License :: OSI Approved :: Apache Software License
Classifier: Operating System :: OS Independent
Requires-Python: >=3.6
